wstools/MIMEAttachment.py
wstools/Namespaces.py
wstools/TimeoutSocket.py
wstools/UserTuple.py
wstools/Utility.py
wstools/WSDLTools.py
wstools/XMLSchema.py
wstools/XMLname.py
wstools/__init__.py
wstools/c14n.py
wstools-0.4.7.dist-info/METADATA
wstools-0.4.7.dist-info/RECORD
wstools-0.4.7.dist-info/WHEEL
wstools-0.4.7.dist-info/entry_points.txt
wstools-0.4.7.dist-info/pbr.json
wstools-0.4.7.dist-info/top_level.txt
