Metadata-Version: 2.1
Name: wstools
Version: 0.4.7
Summary: WSDL parsing services package for Web Services for Python.
Home-page: https://github.com/pycontribs/wstools
Author: Makina Corpus
Author-email: python@makina-corpus.com
Maintainer: Sorin Sbarnea
Maintainer-email: sorin.sbarnea@gmail.com
License: BSD
Keywords: api
Requires-Dist: setuptools (>=17.1)
Requires-Dist: six
